gistory/__init__.py
gistory/bottle.py
gistory/git_object.py
gistory/index.py
gistory/main.py
gistory/views/main.tpl
gistory/views/static/circle.png
gistory/views/static/circle_sm.png
gistory/views/static/github.png
gistory/views/static/help.png
gistory/views/static/join.png
gistory/views/static/lity.min.css
gistory/views/static/lity.min.js
gistory/views/static/movie.png
gistory/views/static/script.js
gistory/views/static/style.css
gistory/views/static/bootstrap/3.3.4/css/bootstrap.min.css
gistory/views/static/bootstrap/3.3.4/js/bootstrap.min.js
gistory/views/static/css/font.css
gistory/views/static/html5shiv/3.7.2/html5shiv.min.js
gistory/views/static/respond/1.4.2/respond.min.js
gistory-0.44.dist-info/METADATA
gistory-0.44.dist-info/RECORD
gistory-0.44.dist-info/WHEEL
gistory-0.44.dist-info/entry_points.txt
gistory-0.44.dist-info/top_level.txt
