Metadata-Version: 2.1
Name: gistory
Version: 0.44
Summary: Tracking your .git changed history
Home-page: https://github.com/egoing/git_changed_history
Author: egoing
Author-email: egoing@gmail.com
License: MIT
Keywords: git
Platform: UNKNOWN
Classifier: Development Status :: 3 - Alpha
Classifier: Intended Audience :: Developers
Classifier: Topic :: Software Development :: Build Tools
Classifier: License :: OSI Approved :: MIT License
Classifier: Programming Language :: Python :: 3
Classifier: Programming Language :: Python :: 3.3
Classifier: Programming Language :: Python :: 3.4
Classifier: Programming Language :: Python :: 3.5
Provides-Extra: dev
Provides-Extra: test
Requires-Dist: six
Provides-Extra: dev
Provides-Extra: test
